media_transcoder/__init__.py
media_transcoder/transcoder.py
nirabo_media_transcoder-0.1.0.dist-info/licenses/LICENSE
nirabo_media_transcoder-0.1.0.dist-info/METADATA
nirabo_media_transcoder-0.1.0.dist-info/WHEEL
nirabo_media_transcoder-0.1.0.dist-info/entry_points.txt
nirabo_media_transcoder-0.1.0.dist-info/top_level.txt
nirabo_media_transcoder-0.1.0.dist-info/RECORD
