Metadata-Version: 2.4
Name: nirabo-media-transcoder
Version: 0.1.0
Summary: A media transcoder with CUDA hardware acceleration support
Author-email: Lyuboslav Petrov <petrov.lyuboslav@gmail.com>
License-Expression: MIT
Project-URL: Homepage, https://github.com/lpetrov/media-transcoder
Project-URL: Bug Tracker, https://github.com/lpetrov/media-transcoder/issues
Project-URL: Documentation, https://github.com/lpetrov/media-transcoder#readme
Project-URL: Source Code, https://github.com/lpetrov/media-transcoder
Classifier: Programming Language :: Python :: 3
Classifier: Operating System :: OS Independent
Classifier: Topic :: Multimedia :: Video :: Conversion
Requires-Python: >=3.8.1
License-File: LICENSE
Requires-Dist: rich>=10.0.0
Requires-Dist: typing-extensions
Provides-Extra: dev
Requires-Dist: pytest>=7.0.0; extra == "dev"
Requires-Dist: pytest-cov>=4.0.0; extra == "dev"
Requires-Dist: black>=23.0.0; extra == "dev"
Requires-Dist: isort>=5.0.0; extra == "dev"
Requires-Dist: flake8>=6.0.0; extra == "dev"
Requires-Dist: mypy>=1.0.0; extra == "dev"
Requires-Dist: twine>=4.0.0; extra == "dev"
Requires-Dist: pdoc>=12.0.0; extra == "dev"
Dynamic: license-file
